exc_errors/aboutproject.py
exc_errors/errors.py
exc_errors-0.0.0.dist-info/LICENSE
exc_errors-0.0.0.dist-info/WHEEL
exc_errors-0.0.0.dist-info/METADATA
exc_errors-0.0.0.dist-info/RECORD
